tkwinterm/__init__.py
tkwinterm/main_winpty.py
tkwinterm/winkey_handler.py
tkwinterm/winlog_handler.py
tkwinterm/winpty_handler.py
tkwinterm/winterminal.py
tkwinterm-0.2.2.dist-info/LICENSE
tkwinterm-0.2.2.dist-info/METADATA
tkwinterm-0.2.2.dist-info/WHEEL
tkwinterm-0.2.2.dist-info/entry_points.txt
tkwinterm-0.2.2.dist-info/top_level.txt
tkwinterm-0.2.2.dist-info/RECORD
