Metadata-Version: 2.1
Name: tkwinterm
Version: 0.2.2
Summary: A fully functional terminal/console widget for Windows, built on Python, Tkinnter and Pyte
Home-page: https://github.com/scottpeterman/tkwinterm
Author: Scott Peterman
Author-email: scottpeterman@gmail.com
License: UNKNOWN
Platform: UNKNOWN
Classifier: Programming Language :: Python :: 3.9
Classifier: License :: OSI Approved :: GNU General Public License v3 (GPLv3)
Classifier: Operating System :: OS Independent
Requires-Python: >=3.9
License-File: LICENSE
Requires-Dist: pywinpty >=2.0.12
Requires-Dist: sv-ttk >=2.6.0
Requires-Dist: pyte >=0.8.2
Requires-Dist: wcwidth >=0.2.13
